Metadata-Version: 1.1
Name: are-compute
Version: 0.1.1
Summary: ARE-compute package from the Saint-Malo poster “Evaluating the Effect of Individualized Treatment Rules Using Observational Data.”
Home-page: UNKNOWN
Author: François Grolleau
Author-email: francois.grolleau@aphp.fr
License: MIT
Platform: UNKNOWN
Classifier: Development Status :: 5 - Production/Stable
Classifier: Intended Audience :: Education
Classifier: Operating System :: Microsoft :: Windows :: Windows 10
Classifier: License :: OSI Approved :: MIT License
Classifier: Programming Language :: Python :: 3
